{
  "type": "Round",
  "round": 1,
  "score": 11,
  "linesCleared": 0,
  "beginOfRoundColorGridBitMask": 0,
  "endOfRoundBitMask": 3715030225421423575797071903,
  "selectedPieces": [
    {
      "name": "HLine5",
      "row": 0,
      "col": 0,
      "rowsCleared": 0,
      "colsCleared": 0
    },
    {
      "name": "VLine5",
      "row": 5,
      "col": 0,
      "rowsCleared": 0,
      "colsCleared": 0
    },
    {
      "name": "Singleton",
      "row": 9,
      "col": 1,
      "rowsCleared": 0,
      "colsCleared": 0
    }
  ],
  "endOfRoundScores": [
    {
      "name": "maximizer",
      "intVal": 53,
      "normalizedVal": 0.828125,
      "weightedVal": 0.5150701033113233
    },
    {
      "name": "avoid middle",
      "intVal": 33,
      "normalizedVal": 0.9883966244725738,
      "weightedVal": 0.16081441632250992
    },
    {
      "name": "occupied",
      "intVal": 11,
      "normalizedVal": 0.89,
      "weightedVal": 0.04580169378718729
    },
    {
      "name": "open rows + cols",
      "intVal": 9,
      "normalizedVal": 0.45,
      "weightedVal": 0.019539216668518773
    },
    {
      "name": "connected open",
      "intVal": 5,
      "normalizedVal": 0.5,
      "weightedVal": 0.02081422186381425
    },
    {
      "name": "spaces on a line",
      "intVal": 20,
      "normalizedVal": 1.0,
      "weightedVal": 0.03381895679879558
    },
    {
      "name": "4 neighbors",
      "intVal": 0,
      "normalizedVal": 1.0,
      "weightedVal": 0.019012215154079293
    },
    {
      "name": "3 neighbors",
      "intVal": 0,
      "normalizedVal": 1.0,
      "weightedVal": 0.018015319977460906
    },
    {
      "name": "2 neighbors",
      "intVal": 7,
      "normalizedVal": 0.8833333333333333,
      "weightedVal": 0.00615616792587723
    },
    {
      "name": "round score",
      "intVal": 11,
      "normalizedVal": 0.027210884353741496,
      "weightedVal": 2.7183700653087487E-5
    }
  ],
  "permutations": [
    {
      "index": 1,
      "winner": true,
      "pieces": [
        {
          "type": "Piece",
          "name": "Singleton"
        },
        {
          "type": "Piece",
          "name": "VLine5"
        },
        {
          "type": "Piece",
          "name": "HLine5"
        }
      ],
      "permutationScores": [
        {
          "name": "maximizer",
          "intVal": 53,
          "normalizedVal": 0.828125,
          "weightedVal": 0.5150701033113233
        },
        {
          "name": "avoid middle",
          "intVal": 33,
          "normalizedVal": 0.9883966244725738,
          "weightedVal": 0.16081441632250992
        },
        {
          "name": "occupied",
          "intVal": 11,
          "normalizedVal": 0.89,
          "weightedVal": 0.04580169378718729
        },
        {
          "name": "open rows + cols",
          "intVal": 9,
          "normalizedVal": 0.45,
          "weightedVal": 0.019539216668518773
        },
        {
          "name": "connected open",
          "intVal": 5,
          "normalizedVal": 0.5,
          "weightedVal": 0.02081422186381425
        },
        {
          "name": "spaces on a line",
          "intVal": 20,
          "normalizedVal": 1.0,
          "weightedVal": 0.03381895679879558
        },
        {
          "name": "4 neighbors",
          "intVal": 0,
          "normalizedVal": 1.0,
          "weightedVal": 0.019012215154079293
        },
        {
          "name": "3 neighbors",
          "intVal": 0,
          "normalizedVal": 1.0,
          "weightedVal": 0.018015319977460906
        },
        {
          "name": "2 neighbors",
          "intVal": 7,
          "normalizedVal": 0.8833333333333333,
          "weightedVal": 0.00615616792587723
        },
        {
          "name": "round score",
          "intVal": 11,
          "normalizedVal": 0.027210884353741496,
          "weightedVal": 2.7183700653087487E-5
        }
      ]
    },
    {
      "index": 2,
      "winner": false,
      "pieces": [
        {
          "type": "Piece",
          "name": "VLine5"
        },
        {
          "type": "Piece",
          "name": "Singleton"
        },
        {
          "type": "Piece",
          "name": "HLine5"
        }
      ],
      "permutationScores": [
        {
          "name": "maximizer",
          "intVal": 53,
          "normalizedVal": 0.828125,
          "weightedVal": 0.5150701033113233
        },
        {
          "name": "avoid middle",
          "intVal": 33,
          "normalizedVal": 0.9883966244725738,
          "weightedVal": 0.16081441632250992
        },
        {
          "name": "occupied",
          "intVal": 11,
          "normalizedVal": 0.89,
          "weightedVal": 0.04580169378718729
        },
        {
          "name": "open rows + cols",
          "intVal": 8,
          "normalizedVal": 0.4,
          "weightedVal": 0.01736819259423891
        },
        {
          "name": "connected open",
          "intVal": 5,
          "normalizedVal": 0.5,
          "weightedVal": 0.02081422186381425
        },
        {
          "name": "spaces on a line",
          "intVal": 20,
          "normalizedVal": 1.0,
          "weightedVal": 0.03381895679879558
        },
        {
          "name": "4 neighbors",
          "intVal": 0,
          "normalizedVal": 1.0,
          "weightedVal": 0.019012215154079293
        },
        {
          "name": "3 neighbors",
          "intVal": 0,
          "normalizedVal": 1.0,
          "weightedVal": 0.018015319977460906
        },
        {
          "name": "2 neighbors",
          "intVal": 6,
          "normalizedVal": 0.9,
          "weightedVal": 0.006272322037686235
        },
        {
          "name": "round score",
          "intVal": 11,
          "normalizedVal": 0.027210884353741496,
          "weightedVal": 2.7183700653087487E-5
        }
      ]
    },
    {
      "index": 3,
      "winner": false,
      "pieces": [
        {
          "type": "Piece",
          "name": "Singleton"
        },
        {
          "type": "Piece",
          "name": "HLine5"
        },
        {
          "type": "Piece",
          "name": "VLine5"
        }
      ],
      "permutationScores": [
        {
          "name": "maximizer",
          "intVal": 53,
          "normalizedVal": 0.828125,
          "weightedVal": 0.5150701033113233
        },
        {
          "name": "avoid middle",
          "intVal": 39,
          "normalizedVal": 0.9862869198312236,
          "weightedVal": 0.1604711624989827
        },
        {
          "name": "occupied",
          "intVal": 11,
          "normalizedVal": 0.89,
          "weightedVal": 0.04580169378718729
        },
        {
          "name": "open rows + cols",
          "intVal": 9,
          "normalizedVal": 0.45,
          "weightedVal": 0.019539216668518773
        },
        {
          "name": "connected open",
          "intVal": 5,
          "normalizedVal": 0.5,
          "weightedVal": 0.02081422186381425
        },
        {
          "name": "spaces on a line",
          "intVal": 20,
          "normalizedVal": 1.0,
          "weightedVal": 0.03381895679879558
        },
        {
          "name": "4 neighbors",
          "intVal": 0,
          "normalizedVal": 1.0,
          "weightedVal": 0.019012215154079293
        },
        {
          "name": "3 neighbors",
          "intVal": 0,
          "normalizedVal": 1.0,
          "weightedVal": 0.018015319977460906
        },
        {
          "name": "2 neighbors",
          "intVal": 7,
          "normalizedVal": 0.8833333333333333,
          "weightedVal": 0.00615616792587723
        },
        {
          "name": "round score",
          "intVal": 11,
          "normalizedVal": 0.027210884353741496,
          "weightedVal": 2.7183700653087487E-5
        }
      ]
    },
    {
      "index": 4,
      "winner": false,
      "pieces": [
        {
          "type": "Piece",
          "name": "HLine5"
        },
        {
          "type": "Piece",
          "name": "Singleton"
        },
        {
          "type": "Piece",
          "name": "VLine5"
        }
      ],
      "permutationScores": [
        {
          "name": "maximizer",
          "intVal": 53,
          "normalizedVal": 0.828125,
          "weightedVal": 0.5150701033113233
        },
        {
          "name": "avoid middle",
          "intVal": 33,
          "normalizedVal": 0.9883966244725738,
          "weightedVal": 0.16081441632250992
        },
        {
          "name": "occupied",
          "intVal": 11,
          "normalizedVal": 0.89,
          "weightedVal": 0.04580169378718729
        },
        {
          "name": "open rows + cols",
          "intVal": 9,
          "normalizedVal": 0.45,
          "weightedVal": 0.019539216668518773
        },
        {
          "name": "connected open",
          "intVal": 5,
          "normalizedVal": 0.5,
          "weightedVal": 0.02081422186381425
        },
        {
          "name": "spaces on a line",
          "intVal": 20,
          "normalizedVal": 1.0,
          "weightedVal": 0.03381895679879558
        },
        {
          "name": "4 neighbors",
          "intVal": 0,
          "normalizedVal": 1.0,
          "weightedVal": 0.019012215154079293
        },
        {
          "name": "3 neighbors",
          "intVal": 0,
          "normalizedVal": 1.0,
          "weightedVal": 0.018015319977460906
        },
        {
          "name": "2 neighbors",
          "intVal": 7,
          "normalizedVal": 0.8833333333333333,
          "weightedVal": 0.00615616792587723
        },
        {
          "name": "round score",
          "intVal": 11,
          "normalizedVal": 0.027210884353741496,
          "weightedVal": 2.7183700653087487E-5
        }
      ]
    },
    {
      "index": 5,
      "winner": false,
      "pieces": [
        {
          "type": "Piece",
          "name": "VLine5"
        },
        {
          "type": "Piece",
          "name": "HLine5"
        },
        {
          "type": "Piece",
          "name": "Singleton"
        }
      ],
      "permutationScores": [
        {
          "name": "maximizer",
          "intVal": 53,
          "normalizedVal": 0.828125,
          "weightedVal": 0.5150701033113233
        },
        {
          "name": "avoid middle",
          "intVal": 33,
          "normalizedVal": 0.9883966244725738,
          "weightedVal": 0.16081441632250992
        },
        {
          "name": "occupied",
          "intVal": 11,
          "normalizedVal": 0.89,
          "weightedVal": 0.04580169378718729
        },
        {
          "name": "open rows + cols",
          "intVal": 9,
          "normalizedVal": 0.45,
          "weightedVal": 0.019539216668518773
        },
        {
          "name": "connected open",
          "intVal": 5,
          "normalizedVal": 0.5,
          "weightedVal": 0.02081422186381425
        },
        {
          "name": "spaces on a line",
          "intVal": 20,
          "normalizedVal": 1.0,
          "weightedVal": 0.03381895679879558
        },
        {
          "name": "4 neighbors",
          "intVal": 0,
          "normalizedVal": 1.0,
          "weightedVal": 0.019012215154079293
        },
        {
          "name": "3 neighbors",
          "intVal": 0,
          "normalizedVal": 1.0,
          "weightedVal": 0.018015319977460906
        },
        {
          "name": "2 neighbors",
          "intVal": 7,
          "normalizedVal": 0.8833333333333333,
          "weightedVal": 0.00615616792587723
        },
        {
          "name": "round score",
          "intVal": 11,
          "normalizedVal": 0.027210884353741496,
          "weightedVal": 2.7183700653087487E-5
        }
      ]
    },
    {
      "index": 6,
      "winner": false,
      "pieces": [
        {
          "type": "Piece",
          "name": "HLine5"
        },
        {
          "type": "Piece",
          "name": "VLine5"
        },
        {
          "type": "Piece",
          "name": "Singleton"
        }
      ],
      "permutationScores": [
        {
          "name": "maximizer",
          "intVal": 53,
          "normalizedVal": 0.828125,
          "weightedVal": 0.5150701033113233
        },
        {
          "name": "avoid middle",
          "intVal": 33,
          "normalizedVal": 0.9883966244725738,
          "weightedVal": 0.16081441632250992
        },
        {
          "name": "occupied",
          "intVal": 11,
          "normalizedVal": 0.89,
          "weightedVal": 0.04580169378718729
        },
        {
          "name": "open rows + cols",
          "intVal": 9,
          "normalizedVal": 0.45,
          "weightedVal": 0.019539216668518773
        },
        {
          "name": "connected open",
          "intVal": 5,
          "normalizedVal": 0.5,
          "weightedVal": 0.02081422186381425
        },
        {
          "name": "spaces on a line",
          "intVal": 20,
          "normalizedVal": 1.0,
          "weightedVal": 0.03381895679879558
        },
        {
          "name": "4 neighbors",
          "intVal": 0,
          "normalizedVal": 1.0,
          "weightedVal": 0.019012215154079293
        },
        {
          "name": "3 neighbors",
          "intVal": 0,
          "normalizedVal": 1.0,
          "weightedVal": 0.018015319977460906
        },
        {
          "name": "2 neighbors",
          "intVal": 7,
          "normalizedVal": 0.8833333333333333,
          "weightedVal": 0.00615616792587723
        },
        {
          "name": "round score",
          "intVal": 11,
          "normalizedVal": 0.027210884353741496,
          "weightedVal": 2.7183700653087487E-5
        }
      ]
    }
  ]
}